Metadata-Version: 2.2
Name: flex-modbus-reader
Version: 0.0.1
Summary: Flex Modbus Reader
Author-email: FlexpowerTech <info@flexpower.tech>, LevchenCom <mklevk@outlook.com>
Maintainer-email: LevchenCom <mklevk@outlook.com>
License: MIT License
Project-URL: Homepage, https://github.com/FlexpowerTech/flex-modbus-reader
Project-URL: Issues, https://github.com/FlexpowerTech/flex-modbus-reader/issues
Keywords: modbus,modbus tcp
Classifier: Programming Language :: Python :: 3
Classifier: Operating System :: OS Independent
Requires-Python: >=3.9
License-File: LICENSE
Requires-Dist: pymodbus<=3.8.3
Requires-Dist: pytest>=8.3.4
